codacy/__init__.py
codacy/reporter.py
codacy_coverage-1.3.10.dist-info/DESCRIPTION.rst
codacy_coverage-1.3.10.dist-info/METADATA
codacy_coverage-1.3.10.dist-info/RECORD
codacy_coverage-1.3.10.dist-info/WHEEL
codacy_coverage-1.3.10.dist-info/entry_points.txt
codacy_coverage-1.3.10.dist-info/metadata.json
codacy_coverage-1.3.10.dist-info/top_level.txt
