Metadata-Version: 2.0
Name: codacy-coverage
Version: 1.3.10
Summary: Codacy coverage reporter for Python
Home-page: https://github.com/codacy/python-codacy-coverage
Author: Codacy
Author-email: team@codacy.com
License: MIT
Keywords: development coverage
Platform: UNKNOWN
Classifier: Development Status :: 5 - Production/Stable
Classifier: Intended Audience :: Developers
Classifier: Topic :: Software Development :: Build Tools
Classifier: License :: OSI Approved :: MIT License
Classifier: Programming Language :: Python :: 2.7
Classifier: Programming Language :: Python :: 3
Requires-Dist: requests (>=2.9.1)
Provides-Extra: dev
Requires-Dist: check-manifest; extra == 'dev'
Provides-Extra: test
Requires-Dist: coverage; extra == 'test'
Requires-Dist: nosetests; extra == 'test'
